hseb/__init__.py
hseb/__main__.py
hseb/preprocess.py
hseb/report.py
hseb/core/__init__.py
hseb/core/config.py
hseb/core/dataset.py
hseb/core/measurement.py
hseb/core/report.py
hseb/core/response.py
hseb/core/submission.py
hseb/engine/__init__.py
hseb/engine/base.py
hseb/engine/elastic.py
hseb/engine/nixiesearch.py
hseb/engine/opensearch.py
hseb/engine/postgres.py
hseb/engine/qdrant.py
hseb/engine/redis.py
hseb/engine/weaviate.py
hseb-0.1.2.dist-info/METADATA
hseb-0.1.2.dist-info/WHEEL
hseb-0.1.2.dist-info/licenses/LICENSE
hseb-0.1.2.dist-info/RECORD
